Workbook

Sheet Cover
B2: GBENGA QUADRI
B3: CFA Candidate | M&A Advisory & Valuation
B5: KESKO CORPORATION
B6: Proposed Acquisition of Tokmanni Group Oyj
B7: M&A Accretion / Dilution Analysis
B9: DEAL RECOMMENDATION
B10: PROCEED WITH CAUTION
B11: Transaction is dilutive at current terms without synergies; accretive with realisable synergies above EUR 25M
B13: Deal Summary:
B14: Acquirer: Kesko Corporation (KESKOB.HE) — EUR 8.0B market cap
B15: Target: Tokmanni Group Oyj (TOKMAN.HE) — EUR 509M market cap
B16: Offer: EUR 11.31/share (30% premium to EUR 8.70 undisturbed)
... B35: March 2026

Sheet Deal_Structure
A1: KESKO / TOKMANNI — DEAL STRUCTURE
A2: GBENGA QUADRI CFA CANDIDATE | D2: All figures in EUR M unless stated
A4: OFFER TERMS
A5: Tokmanni Current Share Price | B5: EUR | C5: 8.7
A6: Offer Premium | B6: % | C6: 0.3
A7: Offer Price Per Share | B7: EUR | C7: =C5*(1+C6) -> 11.31
A8: Tokmanni Shares Outstanding | B8: M | C8: 58.5
A9: Total Equity Consideration | B9: EUR M | C9: =C7*C8 -> 661.635
A11: CONSIDERATION MIX
A12: Cash Consideration % | C12: 0.7
A13: Stock Consideration % | C13: =1-C12 -> 0.3
A14: Cash Amount | B14: EUR M | C14: =C9*C12 -> 463.1445
A15: Stock Amount | B15: EUR M | C15: =C9*C13 -> 198.4905
A16: Kesko Current Share Price | B16: EUR | C16: 20.12
A17: New Kesko Shares Issued | B17: M | C17: =C15/C16 -> 9.865333
A19: SOURCES & USES
A20: Sources | C20: EUR M | E20: Uses
A21: New Debt Issuance | C21: =F21+F22+F23-C22-C23 -> 718.1445 | E21: Equity to Target Shareholders | F21: =C9 -> 661.635
A22: Cash on Hand (Kesko) | C22: 50 | E22: Assumed Target Debt | F22: 280
A23: New Kesko Shares | C23: =C15 -> 198.4905 | E23: Advisory & Transaction Fees | F23: 25
A24: Total Sources | C24: =SUM(C21:C23) -> 966.635 | E24: Total Uses | F24: =F21+F22+F23 -> 966.635
A25: Sources - Uses Check | C25: =C24-F24 -> 0
A27: IMPLIED TRANSACTION MULTIPLES
A28: Tokmanni FY2025 Revenue | C28: 1730
A29: Tokmanni FY2025 EBITDA | C29: 195
A30: Tokmanni FY2025 EBIT | C30: 85
A31: Tokmanni Net Debt (incl. leases) | C31: 920
A33: Implied Enterprise Value | C33: =C9+C31 -> 1581.635
A34: EV / Revenue | C34: =C33/C28 -> 0.91423988
A35: EV / EBITDA | C35: =C33/C29 -> 8.1109487
A36: EV / EBIT | C36: =C33/C30 -> 18.607471
A37: P / E (Offer Price) | C37: =C7/0.59 -> 19.169492 | D37: FY2025 EPS = 0.59
A39: Model follows CFI Financial Modeling Best Practices & Financial Modeling Guidelines
A40: GBENGA QUADRI CFA CANDIDATE | March 2026

Sheet Standalone
A1: STANDALONE FINANCIAL COMPARISON
A2: GBENGA QUADRI CFA CANDIDATE
A4: FY2025 Actuals | B4: Unit | C4: Kesko | D4: Tokmanni | F4: Notes
A5: Revenue | B5: EUR M | C5: 12475 | D5: 1730 | F5: Kesko FY2025 FSR; Tokmanni FY2025 guidance mid
A6: COGS | B6: EUR M | C6: -10680 | D6: -1123
A7: Gross Profit | B7: EUR M | C7: =C5+C6 -> 1795 | D7: =D5+D6 -> 607
A8: Gross Margin | B8: % | C8: =C7/C5 -> 0.14388778 | D8: =D7/D5 -> 0.35086705
A10: SG&A + Other OpEx | B10: EUR M | C10: -640 | D10: -510 | F10: Includes IFRS 16 D&A for Tokmanni
A11: EBITDA | B11: EUR M | C11: 1135 | D11: 195 | F11: Kesko comparable; Tokmanni FY2025 est.
A12: D&A | B12: EUR M | C12: -480 | D12: -110
A13: EBIT (Comparable) | B13: EUR M | C13: 655 | D13: 85 | F13: Kesko Q4 2025 FSR; Tokmanni FY2025 comp
A15: Net Finance Costs | B15: EUR M | C15: -115 | D15: -50 | F15: Kesko incl. lease interest; Tokmanni est.
A16: PBT | B16: EUR M | C16: =C13+C15 -> 540 | D16: =D13+D15 -> 35
A17: Tax (20%) | B17: EUR M | C17: =IF(C16>0,-C16*0.2,0) -> -108 | D17: =IF(D16>0,-D16*0.2,0) -> -7
A18: Net Income | B18: EUR M | C18: =C16+C17 -> 432 | D18: =D16+D17 -> 28
A20: Shares Outstanding | B20: M | C20: 398 | D20: 58.5
A21: EPS | B21: EUR | C21: =C18/C20 -> 1.0854271 | D21: =D18/D20 -> 0.47863248
A22: Share Price | B22: EUR | C22: 20.12 | D22: 8.7 | F22: As of March 2026
A23: Market Cap | B23: EUR M | C23: =C22*C20 -> 8007.76 | D23: =D22*D20 -> 508.95
A24: P/E | B24: x | C24: =C22/C21 -> 18.536481 | D24: =D22/D21 -> 18.176786
A26: Model follows CFI Financial Modeling Best Practices & Financial Modeling Guidelines
A27: GBENGA QUADRI CFA CANDIDATE | March 2026

Sheet Pro_Forma
A1: PRO FORMA COMBINED INCOME STATEMENT
A2: GBENGA QUADRI CFA CANDIDATE
B4: Unit | C4: Kesko Standalone | D4: Tokmanni Standalone | E4: Adjustments | F4: Pro Forma (No Syn.) | G4: Pro Forma (With Syn.)
A5: Revenue | B5: EUR M | C5: =Standalone!C5 -> 12475 | D5: =Standalone!D5 -> 1730 | E5: 0 | F5: =C5+D5+E5 -> 14205 | G5: =F5+Synergies!C16 -> 14245
A7: EBITDA | B7: EUR M | C7: =Standalone!C11 -> 1135 | D7: =Standalone!D11 -> 195 | E7: 0 | F7: =C7+D7+E7 -> 1330 | G7: =F7+Synergies!C9+Synergies!C16 -> 1375
A8: D&A | B8: EUR M | C8: =Standalone!C12 -> -480 | D8: =Standalone!D12 -> -110 | E8: -15 | F8: =C8+D8+E8 -> -605 | G8: =F8 -> -605
A9: EBIT | B9: EUR M | C9: =C7+C8 -> 655 | D9: =D7+D8 -> 85 | E9: =E7+E8 -> -15 | F9: =F7+F8 -> 725 | G9: =G7+G8 -> 770
A11: Net Finance Costs | B11: EUR M | C11: =Standalone!C15 -> -115 | D11: =Standalone!D15 -> -50 | E11: =-Deal_Structure!C21*0.045 -> -32.316502 | F11: =C11+D11+E11 -> -197.3165 | G11: =F11 -> -197.3165
A12: PBT | B12: EUR M | C12: =C9+C11 -> 540 | D12: =D9+D11 -> 35 | E12: =E9+E11 -> -47.316502 | F12: =F9+F11 -> 527.6835 | G12: =G9+G11 -> 572.6835
A13: Tax (20%) | B13: EUR M | C13: =IF(C12>0,-C12*0.2,0) -> -108 | D13: =IF(D12>0,-D12*0.2,0) -> -7 | E13: =IF(E12>0,-E12*0.2,0) -> 0 | F13: =IF(F12>0,-F12*0.2,0) -> -105.5367 | G13: =IF(G12>0,-G12*0.2,0) -> -114.5367
A14: Net Income | B14: EUR M | C14: =C12+C13 -> 432 | D14: =D12+D13 -> 28 | E14: =E12+E13 -> -47.316502 | F14: =F12+F13 -> 422.1468 | G14: =G12+G13 -> 458.1468
A16: Shares Outstanding | B16: M | C16: =Standalone!C20 -> 398 | D16: =Standalone!D20 -> 58.5 | E16: 0 | F16: =C16+Deal_Structure!C17 -> 407.86533 | G16: =F16 -> 407.86533
A17: EPS | B17: EUR | C17: =C14/C16 -> 1.0854271 | F17: =F14/F16 -> 1.0350151 | G17: =G14/G16 -> 1.1232796
A19: Kesko Standalone EPS | C19: =C17 -> 1.0854271 | F19: =C17 -> 1.0854271 | G19: =C17 -> 1.0854271
A20: EPS Accretion / (Dilution) | F20: =F17-F19 -> -0.050411988 | G20: =G17-G19 -> 0.03785244
A21: Accretion / (Dilution) % | F21: =F20/F19 -> -0.046444378 | G21: =G20/G19 -> 0.034873312
A23: Model follows CFI Financial Modeling Best Practices & Financial Modeling Guidelines
A24: GBENGA QUADRI CFA CANDIDATE | March 2026

Sheet Accretion_Dilution
A1: ACCRETION / DILUTION SUMMARY
A2: GBENGA QUADRI CFA CANDIDATE
A4: EPS IMPACT ANALYSIS
C5: Without Synergies | D5: With Synergies
A6: Kesko Standalone EPS | B6: EUR | C6: =Pro_Forma!C17 -> 1.0854271 | D6: =Pro_Forma!C17 -> 1.0854271
A7: Pro Forma EPS | B7: EUR | C7: =Pro_Forma!F17 -> 1.0350151 | D7: =Pro_Forma!G17 -> 1.1232796
A8: EPS Change | B8: EUR | C8: =C7-C6 -> -0.050411988 | D8: =D7-D6 -> 0.03785244
A9: Accretion / (Dilution) % | C9: =C8/C6 -> -0.046444378 | D9: =D8/D6 -> 0.034873312
A10: Verdict | C10: =IF(C8>0,"ACCRETIVE","DILUTIVE") -> DILUTIVE | D10: =IF(D8>0,"ACCRETIVE","DILUTIVE") -> ACCRETIVE
A12: BREAK-EVEN SYNERGY ANALYSIS
A13: EPS Dilution (pre-synergy) | B13: EUR | C13: =C8 -> -0.050411988
A14: Pro Forma Shares | B14: M | C14: =Pro_Forma!F16 -> 407.86533
A15: Dilution in EUR M (pre-tax) | C15: =-C13*C14 -> 20.561302
A16: Tax Rate | C16: 0.2
A17: Break-Even Pre-Tax Synergies | C17: =C15/(1-C16) -> 25.701628
A18: Conclusion: Pre-tax synergies of above amount needed to reach EPS neutrality
A20: Model follows CFI Financial Modeling Best Practices & Financial Modeling Guidelines
A21: GBENGA QUADRI CFA CANDIDATE | March 2026

Sheet Synergies
A1: SYNERGY ANALYSIS
A2: GBENGA QUADRI CFA CANDIDATE
A4: Synergy Category | B4: Unit | C4: Annual Amount | D4: Phase-In (Year 1) | E4: Rationale
A5: COST SYNERGIES
A6: Procurement / Sourcing | B6: EUR M | C6: 20 | D6: 10 | E6: Combined purchasing power for private label, general merchandise
A7: Logistics & Distribution | B7: EUR M | C7: 12 | D7: 5 | E7: Shared Hyvinkaa warehouse; route optimization across ~2,000 stores
A8: SG&A / Corporate Overhead | B8: EUR M | C8: 8 | D8: 4 | E8: Eliminate duplicate HQ functions, IT systems consolidation
A9: Store Network Optimization | B9: EUR M | C9: 5 | D9: 2 | E9: Close overlapping locations; sublease freed space
A10: Total Cost Synergies | C10: =SUM(C6:C9) -> 45 | D10: =SUM(D6:D9) -> 21
A12: REVENUE SYNERGIES
A13: Cross-selling (grocery in Tokmanni) | B13: EUR M | C13: 25 | D13: 8 | E13: K-Plussa loyalty integration; Pirkka products in Tokmanni stores
A14: Online / Omnichannel | B14: EUR M | C14: 10 | D14: 3 | E14: Shared e-commerce platform; Click & Collect across networks
A15: Private Label Expansion | B15: EUR M | C15: 5 | D15: 2 | E15: Extend Tokmanni private label to K-Citymarket non-food
A16: Total Revenue Synergies | C16: =SUM(C13:C15) -> 40 | D16: =SUM(D13:D15) -> 13
A18: SYNERGY SUMMARY
A19: Total Annual Synergies (Run-Rate) | C19: =C10+C16 -> 85
A20: Year 1 Synergies | C20: =D10+D16 -> 34
A22: One-Time Integration Costs | C22: -60 | E22: IT migration, rebranding, severance, store conversions
A23: Integration Period | C23: 2
A25: Model follows CFI Financial Modeling Best Practices & Financial Modeling Guidelines
A26: GBENGA QUADRI CFA CANDIDATE | March 2026

Sheet Credit_Impact
A1: CREDIT / LEVERAGE IMPACT ANALYSIS
A2: GBENGA QUADRI CFA CANDIDATE
B4: Unit | C4: Kesko Pre-Deal | D4: Pro Forma (No Syn.) | E4: Pro Forma (With Syn.)
A5: LEVERAGE METRICS
A6: EBITDA | B6: EUR M | C6: =Standalone!C11 -> 1135 | D6: =Pro_Forma!F7 -> 1330 | E6: =Pro_Forma!G7 -> 1375
A7: Financial Debt (excl. leases) | B7: EUR M | C7: 1345 | D7: =C7+Deal_Structure!C21+Deal_Structure!F22 -> 2343.1445 | E7: =D7 -> 2343.1445
A8: Cash | B8: EUR M | C8: 488 | D8: =C8-Deal_Structure!C22 -> 438 | E8: =D8 -> 438
A9: Net Debt (excl. leases) | C9: =C7-C8 -> 857 | D9: =D7-D8 -> 1905.1445 | E9: =E7-E8 -> 1905.1445
A10: Net Debt / EBITDA | C10: =C9/C6 -> 0.75506608 | D10: =D9/D6 -> 1.4324395 | E10: =E9/E6 -> 1.3855596
A12: Total Debt / EBITDA (incl. leases) | B12: x | C12: 3.1 | D12: =(D7+2151+Deal_Structure!C31)/D6 -> 4.0707853 | E12: =(E7+2151+Deal_Structure!C31)/E6 -> 3.9375596
A13: Interest Coverage (EBITDA/Int.) | C13: =C6/(-Pro_Forma!C11) -> 9.8695652 | D13: =D6/(-Pro_Forma!D11) -> 26.6 | E13: =E6/(-Pro_Forma!E11) -> 42.547921
A15: CREDIT ASSESSMENT
A16: Pre-deal leverage is investment-grade (1.1x Net Debt/EBITDA excl. leases).
A17: Post-deal leverage increases meaningfully due to acquisition debt and assumed Tokmanni debt.
A18: With synergies, EBITDA improves and leverage ratios improve modestly.
A19: Rating agencies would likely place Kesko on negative outlook pending integration execution.
A21: Model follows CFI Financial Modeling Best Practices & Financial Modeling Guidelines
A22: GBENGA QUADRI CFA CANDIDATE | March 2026

Sheet Sensitivity
A1: SENSITIVITY ANALYSIS
A2: GBENGA QUADRI CFA CANDIDATE
A4: EPS ACCRETION / (DILUTION) %
A5: Offer Premium vs. Annual Synergies (EUR M)
A6: Premium\Syn | B6: 0 | C6: 25 | D6: 45 | E6: 65 | F6: 85
A7: 0.15 | B7: -0.009 | C7: 0.018 | D7: 0.042 | E7: 0.067 | F7: 0.091
A8: 0.2 | B8: -0.021 | C8: 0.006 | D8: 0.03 | E8: 0.054 | F8: 0.078
A9: 0.25 | B9: -0.032 | C9: -0.006 | D9: 0.018 | E9: 0.042 | F9: 0.066
A10: 0.3 | B10: -0.043 | C10: -0.017 | D10: 0.007 | E10: 0.031 | F10: 0.054
A11: 0.35 | B11: -0.054 | C11: -0.028 | D11: -0.004 | E11: 0.02 | F11: 0.043
A12: 0.4 | B12: -0.064 | C12: -0.039 | D12: -0.015 | E12: 0.009 | F12: 0.033
A15: Cash % in Deal vs. Annual Synergies (EUR M)
A16: Cash%\Syn | B16: 0 | C16: 25 | D16: 45 | E16: 65 | F16: 85
A17: 0.5 | B17: -0.02 | C17: 0.004 | D17: 0.028 | E17: 0.052 | F17: 0.076
A18: 0.6 | B18: -0.032 | C18: -0.006 | D18: 0.018 | E18: 0.042 | F18: 0.065
A19: 0.7 | B19: -0.043 | C19: -0.017 | D19: 0.007 | E19: 0.031 | F19: 0.054
A20: 0.8 | B20: -0.053 | C20: -0.027 | D20: -0.003 | E20: 0.021 | F20: 0.045
A21: 0.9 | B21: -0.062 | C21: -0.036 | D21: -0.012 | E21: 0.012 | F21: 0.036
A22: 1 | B22: -0.07 | C22: -0.044 | D22: -0.02 | E22: 0.004 | F22: 0.028
A24: Green = accretive; Red = dilutive
A25: Dark green = base case (30% premium, 70% cash, EUR 45M synergies)
A27: Model follows CFI Financial Modeling Best Practices & Financial Modeling Guidelines
A28: GBENGA QUADRI CFA CANDIDATE | March 2026
